fbterminal
