Metadata-Version: 1.0
Name: fbterminal
Version: 0.2.1
Summary: Access Facebook on Terminal
Home-page: http://decached.com/fbterminal
Author: Akash Kothawale
Author-email: io@decached.com
License: MIT
Platform: UNKNOWN
